django_tui/__about__.py
django_tui/__init__.py
django_tui/management/__init__.py
django_tui/management/commands/__init__.py
django_tui/management/commands/ish.py
django_tui/management/commands/trogon.scss
django_tui/management/commands/tui.py
django_tui-24.5.dist-info/METADATA
django_tui-24.5.dist-info/WHEEL
django_tui-24.5.dist-info/licenses/LICENSE.txt
django_tui-24.5.dist-info/RECORD
