Metadata-Version: 2.3
Name: django-tui
Version: 24.5
Summary: Inspect and run Django Commands in a text-based user interface (TUI).
Project-URL: Documentation, https://github.com/anze3db/django-tui#readme
Project-URL: Issues, https://github.com/anze3db/django-tui/issues
Project-URL: Source, https://github.com/anze3db/django-tui
Project-URL: Changelog, https://github.com/anze3db/django-tui/blob/main/CHANGELOG.md
Project-URL: Mastodon, https://fosstodon.org/@anze3db
Project-URL: Twitter, https://twitter.com/anze3db
Author-email: Anže Pečar <anze@pecar.me>
License-Expression: MIT
License-File: LICENSE.txt
Keywords: django,textual,tui
Classifier: Development Status :: 5 - Production/Stable
Classifier: Framework :: Django
Classifier: Framework :: Django :: 3.2
Classifier: Framework :: Django :: 4.0
Classifier: Framework :: Django :: 4.1
Classifier: Framework :: Django :: 4.2
Classifier: Framework :: Django :: 5.0
Classifier: Framework :: Django :: 5.1
Classifier: Programming Language :: Python
Classifier: Programming Language :: Python :: 3.8
Classifier: Programming Language :: Python :: 3.9
Classifier: Programming Language :: Python :: 3.10
Classifier: Programming Language :: Python :: 3.11
Classifier: Programming Language :: Python :: 3.12
Classifier: Programming Language :: Python :: Implementation :: CPython
Classifier: Programming Language :: Python :: Implementation :: PyPy
Requires-Python: >=3.8
Requires-Dist: django>=3.2
Requires-Dist: textual>=0.64.0
Requires-Dist: trogon
